chat_with_arduino/__init__.py
chat_with_arduino/server.py
chat_with_arduino-0.4.5.dist-info/METADATA
chat_with_arduino-0.4.5.dist-info/WHEEL
chat_with_arduino-0.4.5.dist-info/entry_points.txt
chat_with_arduino-0.4.5.dist-info/RECORD
