Metadata-Version: 2.4
Name: chat-with-arduino
Version: 0.4.5
Summary: Control your Arduino microcontroller using LLMs
License: MIT
Keywords: arduino,automation,http,llm,mcp
Requires-Python: >=3.10
Requires-Dist: mcp[cli]>=1.3.0
Requires-Dist: pyserial>=3.5
